<?xml version="1.0" encoding="UTF-8"?>
<objects serializationModel="Studio.02.01.00">
	<object class="AudioFile" id="{549a39a1-cc50-40f0-af05-4304bcb8144f}">
		<property name="assetPath">
			<value>clickSlime_04.wav</value>
		</property>
		<property name="frequencyInKHz">
			<value>44.0999985</value>
		</property>
		<property name="channelCount">
			<value>2</value>
		</property>
		<property name="length">
			<value>0.049977324263038546</value>
		</property>
		<relationship name="masterAssetFolder">
			<destination>{5514b572-c26a-43c4-b9a5-ca9b1bb17c0f}</destination>
		</relationship>
	</object>
</objects>
